phoenix/otel/__init__.py
phoenix/otel/otel.py
phoenix/otel/settings.py
arize_phoenix_otel_multi-0.7.1.dist-info/METADATA
arize_phoenix_otel_multi-0.7.1.dist-info/WHEEL
arize_phoenix_otel_multi-0.7.1.dist-info/licenses/IP_NOTICE
arize_phoenix_otel_multi-0.7.1.dist-info/licenses/LICENSE
arize_phoenix_otel_multi-0.7.1.dist-info/RECORD
