Metadata-Version: 2.4
Name: arize-phoenix-otel-multi
Version: 0.7.1
Summary: LLM Observability
Project-URL: Documentation, https://docs.arize.com/phoenix/
Project-URL: Issues, https://github.com/Arize-ai/phoenix/issues
Project-URL: Source, https://github.com/Arize-ai/phoenix
Author-email: Arize AI <phoenix-devs@arize.com>
License: Elastic-2.0
License-File: IP_NOTICE
License-File: LICENSE
Keywords: Explainability,Monitoring,Observability
Classifier: Programming Language :: Python
Classifier: Programming Language :: Python :: 3.8
Classifier: Programming Language :: Python :: 3.9
Classifier: Programming Language :: Python :: 3.10
Classifier: Programming Language :: Python :: 3.11
Classifier: Programming Language :: Python :: 3.12
Classifier: Programming Language :: Python :: 3.13
Requires-Python: <3.14,>=3.8
Requires-Dist: openinference-instrumentation>=0.1.21
Requires-Dist: openinference-semantic-conventions>=0.1.9
Requires-Dist: opentelemetry-exporter-otlp
Requires-Dist: opentelemetry-proto>=1.12.0
Requires-Dist: opentelemetry-sdk
Requires-Dist: opentelemetry-semantic-conventions
Requires-Dist: typing-extensions<5,>=4.5
Provides-Extra: test
